<annotation>
	<folder>images</folder>
	<filename>IMG_4424.jpg</filename>
	<path>/media/sf_ShareFolder/orange/images/IMG_4424.jpg</path>
	<source>
		<database>Unknown</database>
	</source>
	<size>
		<width>4032</width>
		<height>3024</height>
		<depth>3</depth>
	</size>
	<segmented>0</segmented>
	<object>
		<name>mature</name>
		<pose>Unspecified</pose>
		<truncated>0</truncated>
		<difficult>0</difficult>
		<bndbox>
			<xmin>3013</xmin>
			<ymin>1479</ymin>
			<xmax>3810</xmax>
			<ymax>2344</ymax>
		</bndbox>
	</object>
	<object>
		<name>flower</name>
		<pose>Unspecified</pose>
		<truncated>0</truncated>
		<difficult>0</difficult>
		<bndbox>
			<xmin>1507</xmin>
			<ymin>282</ymin>
			<xmax>1736</xmax>
			<ymax>452</ymax>
		</bndbox>
	</object>
	<object>
		<name>mature</name>
		<pose>Unspecified</pose>
		<truncated>0</truncated>
		<difficult>0</difficult>
		<bndbox>
			<xmin>1319</xmin>
			<ymin>1291</ymin>
			<xmax>1480</xmax>
			<ymax>1458</ymax>
		</bndbox>
	</object>
</annotation>
