<annotation>
	<folder>images</folder>
	<filename>IMG_4256.jpg</filename>
	<path>/media/sf_VMshare/orange/images/IMG_4256.jpg</path>
	<source>
		<database>Unknown</database>
	</source>
	<size>
		<width>3024</width>
		<height>3024</height>
		<depth>3</depth>
	</size>
	<segmented>0</segmented>
	<object>
		<name>mature</name>
		<pose>Unspecified</pose>
		<truncated>0</truncated>
		<difficult>0</difficult>
		<bndbox>
			<xmin>1633</xmin>
			<ymin>588</ymin>
			<xmax>2470</xmax>
			<ymax>1446</ymax>
		</bndbox>
	</object>
	<object>
		<name>mature</name>
		<pose>Unspecified</pose>
		<truncated>0</truncated>
		<difficult>0</difficult>
		<bndbox>
			<xmin>670</xmin>
			<ymin>1630</ymin>
			<xmax>1470</xmax>
			<ymax>2440</ymax>
		</bndbox>
	</object>
	<object>
		<name>mature</name>
		<pose>Unspecified</pose>
		<truncated>0</truncated>
		<difficult>0</difficult>
		<bndbox>
			<xmin>380</xmin>
			<ymin>677</ymin>
			<xmax>1059</xmax>
			<ymax>1240</ymax>
		</bndbox>
	</object>
</annotation>
