<annotation>
	<folder>images</folder>
	<filename>IMG_4101.jpg</filename>
	<path>/media/sf_VMshare/orange/images/IMG_4101.jpg</path>
	<source>
		<database>Unknown</database>
	</source>
	<size>
		<width>3024</width>
		<height>3024</height>
		<depth>3</depth>
	</size>
	<segmented>0</segmented>
	<object>
		<name>mature</name>
		<pose>Unspecified</pose>
		<truncated>0</truncated>
		<difficult>0</difficult>
		<bndbox>
			<xmin>1964</xmin>
			<ymin>793</ymin>
			<xmax>2538</xmax>
			<ymax>1382</ymax>
		</bndbox>
	</object>
	<object>
		<name>mature</name>
		<pose>Unspecified</pose>
		<truncated>1</truncated>
		<difficult>0</difficult>
		<bndbox>
			<xmin>1654</xmin>
			<ymin>2667</ymin>
			<xmax>2328</xmax>
			<ymax>3024</ymax>
		</bndbox>
	</object>
	<object>
		<name>mature</name>
		<pose>Unspecified</pose>
		<truncated>0</truncated>
		<difficult>0</difficult>
		<bndbox>
			<xmin>1082</xmin>
			<ymin>1859</ymin>
			<xmax>1669</xmax>
			<ymax>2477</ymax>
		</bndbox>
	</object>
</annotation>
