<annotation>
	<folder>images</folder>
	<filename>IMG_4258.jpg</filename>
	<path>/media/sf_VMshare/orange/images/IMG_4258.jpg</path>
	<source>
		<database>Unknown</database>
	</source>
	<size>
		<width>3024</width>
		<height>3024</height>
		<depth>3</depth>
	</size>
	<segmented>0</segmented>
	<object>
		<name>mature</name>
		<pose>Unspecified</pose>
		<truncated>0</truncated>
		<difficult>0</difficult>
		<bndbox>
			<xmin>1041</xmin>
			<ymin>1833</ymin>
			<xmax>1486</xmax>
			<ymax>2302</ymax>
		</bndbox>
	</object>
	<object>
		<name>mature</name>
		<pose>Unspecified</pose>
		<truncated>0</truncated>
		<difficult>0</difficult>
		<bndbox>
			<xmin>73</xmin>
			<ymin>561</ymin>
			<xmax>404</xmax>
			<ymax>851</ymax>
		</bndbox>
	</object>
	<object>
		<name>mature</name>
		<pose>Unspecified</pose>
		<truncated>1</truncated>
		<difficult>0</difficult>
		<bndbox>
			<xmin>1</xmin>
			<ymin>1465</ymin>
			<xmax>304</xmax>
			<ymax>1845</ymax>
		</bndbox>
	</object>
	<object>
		<name>mature</name>
		<pose>Unspecified</pose>
		<truncated>0</truncated>
		<difficult>0</difficult>
		<bndbox>
			<xmin>820</xmin>
			<ymin>927</ymin>
			<xmax>1080</xmax>
			<ymax>1157</ymax>
		</bndbox>
	</object>
	<object>
		<name>mature</name>
		<pose>Unspecified</pose>
		<truncated>0</truncated>
		<difficult>0</difficult>
		<bndbox>
			<xmin>1472</xmin>
			<ymin>2138</ymin>
			<xmax>1744</xmax>
			<ymax>2490</ymax>
		</bndbox>
	</object>
	<object>
		<name>mature</name>
		<pose>Unspecified</pose>
		<truncated>1</truncated>
		<difficult>0</difficult>
		<bndbox>
			<xmin>1499</xmin>
			<ymin>2655</ymin>
			<xmax>1809</xmax>
			<ymax>3024</ymax>
		</bndbox>
	</object>
</annotation>
