<annotation>
	<folder>images</folder>
	<filename>1528863925.0724823.jpg</filename>
	<path>E:\MicrosoftOneDrive\OneDrive\Working\gestureSensor\dataset\v1\images\1528863925.0724823.jpg</path>
	<source>
		<database>Unknown</database>
	</source>
	<size>
		<width>640</width>
		<height>480</height>
		<depth>3</depth>
	</size>
	<segmented>0</segmented>
	<object>
		<name>palm</name>
		<pose>Unspecified</pose>
		<truncated>0</truncated>
		<difficult>0</difficult>
		<bndbox>
			<xmin>316</xmin>
			<ymin>140</ymin>
			<xmax>400</xmax>
			<ymax>243</ymax>
		</bndbox>
	</object>
</annotation>
