<annotation>
	<folder>images</folder>
	<filename>csi_1600x1600_20180118_111034.jpg</filename>
	<path>E:\MicrosoftOneDrive\OneDrive\Working\datasets\actions\images\csi_1600x1600_20180118_111034.jpg</path>
	<source>
		<database>Unknown</database>
	</source>
	<size>
		<width>1600</width>
		<height>1600</height>
		<depth>3</depth>
	</size>
	<segmented>0</segmented>
	<object>
		<name>head</name>
		<pose>Unspecified</pose>
		<truncated>0</truncated>
		<difficult>0</difficult>
		<bndbox>
			<xmin>176</xmin>
			<ymin>257</ymin>
			<xmax>295</xmax>
			<ymax>370</ymax>
		</bndbox>
	</object>
	<object>
		<name>head</name>
		<pose>Unspecified</pose>
		<truncated>0</truncated>
		<difficult>0</difficult>
		<bndbox>
			<xmin>180</xmin>
			<ymin>1353</ymin>
			<xmax>285</xmax>
			<ymax>1472</ymax>
		</bndbox>
	</object>
	<object>
		<name>head</name>
		<pose>Unspecified</pose>
		<truncated>0</truncated>
		<difficult>0</difficult>
		<bndbox>
			<xmin>1217</xmin>
			<ymin>268</ymin>
			<xmax>1336</xmax>
			<ymax>389</ymax>
		</bndbox>
	</object>
	<object>
		<name>head</name>
		<pose>Unspecified</pose>
		<truncated>0</truncated>
		<difficult>0</difficult>
		<bndbox>
			<xmin>1466</xmin>
			<ymin>1374</ymin>
			<xmax>1561</xmax>
			<ymax>1493</ymax>
		</bndbox>
	</object>
	<object>
		<name>standing</name>
		<pose>Unspecified</pose>
		<truncated>0</truncated>
		<difficult>0</difficult>
		<bndbox>
			<xmin>1144</xmin>
			<ymin>1147</ymin>
			<xmax>1561</xmax>
			<ymax>1497</ymax>
		</bndbox>
	</object>
	<object>
		<name>sitting</name>
		<pose>Unspecified</pose>
		<truncated>0</truncated>
		<difficult>0</difficult>
		<bndbox>
			<xmin>164</xmin>
			<ymin>999</ymin>
			<xmax>517</xmax>
			<ymax>1466</ymax>
		</bndbox>
	</object>
	<object>
		<name>sitting</name>
		<pose>Unspecified</pose>
		<truncated>0</truncated>
		<difficult>0</difficult>
		<bndbox>
			<xmin>150</xmin>
			<ymin>257</ymin>
			<xmax>517</xmax>
			<ymax>696</ymax>
		</bndbox>
	</object>
	<object>
		<name>sitting</name>
		<pose>Unspecified</pose>
		<truncated>0</truncated>
		<difficult>0</difficult>
		<bndbox>
			<xmin>950</xmin>
			<ymin>247</ymin>
			<xmax>1358</xmax>
			<ymax>724</ymax>
		</bndbox>
	</object>
	<object>
		<name>chair</name>
		<pose>Unspecified</pose>
		<truncated>0</truncated>
		<difficult>0</difficult>
		<bndbox>
			<xmin>1045</xmin>
			<ymin>845</ymin>
			<xmax>1460</xmax>
			<ymax>1186</ymax>
		</bndbox>
	</object>
</annotation>
